tests/helpers/__init__.py
tests/helpers/cuda_check.py
time_series_predictor/__init__.py
time_series_predictor/l1_regularized_nnr.py
time_series_predictor/min_max_scaler.py
time_series_predictor/time_series_predictor.py
time_series_predictor/sklearn/__init__.py
time_series_predictor/sklearn/base.py
time_series_predictor/sklearn/__pycache__/__init__.cpython-39.pyc
time_series_predictor/sklearn/__pycache__/base.cpython-39.pyc
time_series_predictor/sklearn/compose/__init__.py
time_series_predictor/sklearn/compose/_target.py
time_series_predictor/sklearn/compose/__pycache__/__init__.cpython-39.pyc
time_series_predictor/sklearn/compose/__pycache__/_target.cpython-39.pyc
time_series_predictor/sklearn/linear_model/__init__.py
time_series_predictor/sklearn/linear_model/_base.py
time_series_predictor/sklearn/linear_model/__pycache__/__init__.cpython-39.pyc
time_series_predictor/sklearn/linear_model/__pycache__/_base.cpython-39.pyc
time_series_predictor/sklearn/novel/__init__.py
time_series_predictor/sklearn/novel/sample_predict.py
time_series_predictor/sklearn/novel/__pycache__/__init__.cpython-39.pyc
time_series_predictor/sklearn/novel/__pycache__/sample_predict.cpython-39.pyc
time_series_predictor-3.0.6.dist-info/LICENSE
time_series_predictor-3.0.6.dist-info/METADATA
time_series_predictor-3.0.6.dist-info/WHEEL
time_series_predictor-3.0.6.dist-info/top_level.txt
time_series_predictor-3.0.6.dist-info/RECORD
