Metadata-Version: 2.1
Name: time-series-predictor
Version: 3.0.6
Summary: Time Series Predictor
Home-page: https://time-series-predictor.readthedocs.io/
Author: Daniel Kaminski de Souza
Author-email: daniel@kryptonunite.com
License: UNKNOWN
Platform: UNKNOWN
Classifier: Programming Language :: Python :: 3
Classifier: License :: OSI Approved :: GNU General Public License v3 (GPLv3)
Classifier: Operating System :: OS Independent
Requires-Python: >=3.6
Requires-Dist: IPython
Requires-Dist: psutil
Requires-Dist: skorch
Requires-Dist: time-series-dataset
Provides-Extra: dev
Requires-Dist: autopep8 ; extra == 'dev'
Requires-Dist: bumpversion ; extra == 'dev'
Requires-Dist: pylint ; extra == 'dev'
Requires-Dist: python-dotenv ; extra == 'dev'
Requires-Dist: python-dotenv[cli] ; extra == 'dev'
Requires-Dist: twine ; extra == 'dev'
Requires-Dist: wheel ; extra == 'dev'
Provides-Extra: docs
Requires-Dist: flights-time-series-dataset ; extra == 'docs'
Requires-Dist: ipykernel ; extra == 'docs'
Requires-Dist: jupyterlab ; extra == 'docs'
Requires-Dist: matplotlib ; extra == 'docs'
Requires-Dist: nbsphinx ; extra == 'docs'
Requires-Dist: oze-dataset ; extra == 'docs'
Requires-Dist: pandas ; extra == 'docs'
Requires-Dist: python-dotenv ; extra == 'docs'
Requires-Dist: recommonmark ; extra == 'docs'
Requires-Dist: rstcheck ; extra == 'docs'
Requires-Dist: seaborn ; extra == 'docs'
Requires-Dist: sklearn ; extra == 'docs'
Requires-Dist: sphinx ; extra == 'docs'
Requires-Dist: sphinx-autodoc-typehints ; extra == 'docs'
Requires-Dist: sphinx-rtd-theme ; extra == 'docs'
Requires-Dist: sphinxcontrib-svg2pdfconverter ; extra == 'docs'
Requires-Dist: time-series-models ; extra == 'docs'
Provides-Extra: test
Requires-Dist: flights-time-series-dataset ; extra == 'test'
Requires-Dist: oze-dataset ; extra == 'test'
Requires-Dist: pytest-cov ; extra == 'test'
Requires-Dist: pytest (>=4.6) ; extra == 'test'
Requires-Dist: python-dotenv ; extra == 'test'
Requires-Dist: time-series-models ; extra == 'test'
